gandi_api_livedns/__init__.py
gandi_api_livedns/const.py
gandi_api_livedns/gandi.py
gandi_api_livedns-0.3.0.dist-info/LICENSE
gandi_api_livedns-0.3.0.dist-info/METADATA
gandi_api_livedns-0.3.0.dist-info/WHEEL
gandi_api_livedns-0.3.0.dist-info/top_level.txt
gandi_api_livedns-0.3.0.dist-info/RECORD
