Metadata-Version: 2.1
Name: gandi-api-livedns
Version: 0.3.0
Summary: Gandi.net live DNS client Api
Home-page: https://github.com/flexy2dd/gandi-api-livedns
Author: Flexy2dd
Author-email: flexy2dd@blackdev.com
License: UNKNOWN
Keywords: gandi.net,api,dns
Platform: UNKNOWN
Classifier: Programming Language :: Python :: 3
Classifier: License :: OSI Approved :: MIT License
Classifier: Operating System :: OS Independent
Classifier: Development Status :: 4 - Beta
Classifier: Topic :: Software Development :: Build Tools
Requires-Python: >=3.6
License-File: LICENSE
Requires-Dist: requests (>=^2.25.0)
